{"id":19710262,"id_str":"19710262","name":"Paul Atkinson","screen_name":"paulscotz","location":"Edinburgh","url":"http:\/\/www.parequity.com","description":"VC and Angel Investor in Innovation & Technology","protected":false,"followers_count":172,"friends_count":189,"listed_count":0,"created_at":"Thu Jan 29 13:23:58 +0000 2009","favourites_count":0,"utc_offset":null,"time_zone":null,"geo_enabled":false,"verified":false,"statuses_count":100,"lang":"en","status":{"created_at":"Sat Nov 10 16:54:54 +0000 2012","id":267309367647428609,"id_str":"267309367647428609","text":"Bannockburn 2014 - should be some event... http:\/\/t.co\/cXmPuqI6","source":"\u003ca href=\"http:\/\/www.linkedin.com\/\" rel=\"nofollow\"\u003eLinkedIn\u003c\/a\u003e","truncated":false,"in_reply_to_status_id":null,"in_reply_to_status_id_str":null,"in_reply_to_user_id":null,"in_reply_to_user_id_str":null,"in_reply_to_screen_name":null,"geo":null,"coordinates":null,"place":null,"contributors":null,"retweet_count":0,"favorited":false,"retweeted":false,"possibly_sensitive":false},"contributors_enabled":false,"is_translator":false,"profile_background_color":"C0DEED","profile_background_image_url":"http:\/\/a0.twimg.com\/images\/themes\/theme1\/bg.png","profile_background_image_url_https":"https:\/\/si0.twimg.com\/images\/themes\/theme1\/bg.png","profile_background_tile":false,"profile_image_url":"http:\/\/a0.twimg.com\/sticky\/default_profile_images\/default_profile_5_normal.png","profile_image_url_https":"https:\/\/si0.twimg.com\/sticky\/default_profile_images\/default_profile_5_normal.png","profile_link_color":"0084B4","profile_sidebar_border_color":"C0DEED","profile_sidebar_fill_color":"DDEEF6","profile_text_color":"333333","profile_use_background_image":true,"default_profile":true,"default_profile_image":true,"following":null,"follow_request_sent":null,"notifications":null},
