{"id":42301990,"id_str":"42301990","name":"John Verostek","screen_name":"johnverostek","location":"Cambridge, MA","url":"http:\/\/johnverostek.com","description":"","protected":false,"followers_count":93,"friends_count":397,"listed_count":8,"created_at":"Sun May 24 23:18:30 +0000 2009","favourites_count":1,"utc_offset":-18000,"time_zone":"Eastern Time (US & Canada)","geo_enabled":false,"verified":false,"statuses_count":756,"lang":"en","status":{"created_at":"Sun Nov 11 06:27:40 +0000 2012","id":267513910091972608,"id_str":"267513910091972608","text":"slowly, but surely, have ran the first part of Echonest Million Song Dataset (MSD) Map\/Reduce example. Now can sleep in peace! #musichackday","source":"web","truncated":false,"in_reply_to_status_id":null,"in_reply_to_status_id_str":null,"in_reply_to_user_id":null,"in_reply_to_user_id_str":null,"in_reply_to_screen_name":null,"geo":null,"coordinates":null,"place":null,"contributors":null,"retweet_count":0,"favorited":false,"retweeted":false},"contributors_enabled":false,"is_translator":false,"profile_background_color":"9AE4E8","profile_background_image_url":"http:\/\/a0.twimg.com\/profile_background_images\/16503918\/WP_Surfing_01.jpg","profile_background_image_url_https":"https:\/\/si0.twimg.com\/profile_background_images\/16503918\/WP_Surfing_01.jpg","profile_background_tile":true,"profile_image_url":"http:\/\/a0.twimg.com\/profile_images\/228778252\/48049249J_normal.jpg","profile_image_url_https":"https:\/\/si0.twimg.com\/profile_images\/228778252\/48049249J_normal.jpg","profile_link_color":"0084B4","profile_sidebar_border_color":"BDDCAD","profile_sidebar_fill_color":"DDFFCC","profile_text_color":"333333","profile_use_background_image":true,"default_profile":false,"default_profile_image":false,"following":null,"follow_request_sent":null,"notifications":null},
